[
    {
        "nombre": "Sanguche de pollo",
        "descripcion": "Sanguche hecho con los mejores pollos seleccionado de nuestros especialistas en aves y del buen comer, con los agregados que vos quieras y nuestro toque especial AMOR 游땔.",
        "sku": "SAN-POLLO-001",
        "ingredientes": [
            "pan de miga",
            "pollo",
            "tomate",
            "lechuga",
            "queso",
            "mayonesa casera"
        ],
        "imagen": "/images/imagen2.png",
        "categoria": "Sanguchito",
        "aptitud": "",
        "tama침o": "Mediano",
        "precio": 3500
    },
    {
        "nombre": "Sanguche de JyQ",
        "descripcion": "Un clasico de la vida al que le podes dar un toque especial a tu propio gusto y sin juzgarte sumando claramente nuestro propio sello de LOVE 游봃.",
        "sku": "SAN-JyQ-002",
        "ingredientes": [
            "pan de miga",
            "jamon",
            "tomate",
            "lechuga",
            "queso",
            "mayonesa casera"
        ],
        "imagen": "/images/imagen3.png",
        "categoria": "Sanguchito",
        "aptitud": "",
        "tama침o": "Mediano",
        "precio": 3800
    },
    {
        "nombre": "Sanguche charcutero",
        "descripcion": "ara vos que sos un carnivoro voraz te traemos este sanguche charcutero con los mejores fiambres exportados del otro lado del gran charco sumandole nuestro toque especial de AMOR 游땘  hacen la mejor combinacion posible del charcutero 游녡.",
        "sku": "SAN-CHARCUTERO-003",
        "ingredientes": [
            "pan frances",
            "salame",
            "mortadela",
            "jamon",
            "cebolla",
            "tomate",
            "lechuga",
            "queso",
            "mayonesa casera"
        ],
        "imagen": "/images/imagen4.png",
        "categoria": "Sanguchito",
        "aptitud": "",
        "tama침o": "Grande",
        "precio": 6000
    },
    {
        "nombre": "Sanguche de Mila",
        "descripcion": "El infaltable, el esencial, el tucumano, si asi es el sanguche de milanesa hecho con la carne de las mejores vacas de nuestra tierra, armalo como quieras total queda rico siempre y nuestro infaltable toque siempre estara 游눘 de la milanga.",
        "sku": "SAN-MILA-004",
        "ingredientes": [
            "pan frances",
            "mila de carne",
            "jamon",
            "tomate",
            "lechuga",
            "queso",
            "mayonesa casera"
        ],
        "imagen": "/images/imagen5.png",
        "categoria": "Sanguchito",
        "aptitud": "",
        "tama침o": "Grande",
        "precio": 5000
    }
]